mkdocs_sql/__init__.py
mkdocs_sql/plugin.py
mkdocs_sql/version.py
mkdocs_sql-0.2.4.dist-info/LICENSE
mkdocs_sql-0.2.4.dist-info/METADATA
mkdocs_sql-0.2.4.dist-info/WHEEL
mkdocs_sql-0.2.4.dist-info/entry_points.txt
mkdocs_sql-0.2.4.dist-info/top_level.txt
mkdocs_sql-0.2.4.dist-info/RECORD
