Metadata-Version: 2.1
Name: mkdocs_sql
Version: 0.2.4
Summary: A MkDocs plugin for executing and displaying SQL queries
Home-page: https://github.com/ivishalgandhi/mkdocs-sql
Author: Vishal Gandhi
Author-email: Vishal Gandhi <igandhivishal@gmail.com>
Project-URL: Homepage, https://github.com/ivishalgandhi/mkdocs-sql
Project-URL: Repository, https://github.com/ivishalgandhi/mkdocs-sql
Project-URL: Issues, https://github.com/ivishalgandhi/mkdocs-sql/issues
Classifier: Programming Language :: Python :: 3
Classifier: License :: OSI Approved :: MIT License
Classifier: Operating System :: OS Independent
Classifier: Framework :: MkDocs
Classifier: Topic :: Documentation
Requires-Python: >=3.7
License-File: LICENSE
Requires-Dist: mkdocs ~=1.6.0
Requires-Dist: pandas >=2.2.3
Requires-Dist: tabulate >=0.9.0
Requires-Dist: pyyaml >=6.0.2
Requires-Dist: duckdb >=0.10.0
